repo_stream/__init__.py
repo_stream/__main__.py
repo_stream/git.py
repo_stream/github.py
repo_stream/update.py
repo_stream-1.3.1.dist-info/LICENSE
repo_stream-1.3.1.dist-info/METADATA
repo_stream-1.3.1.dist-info/WHEEL
repo_stream-1.3.1.dist-info/entry_points.txt
repo_stream-1.3.1.dist-info/top_level.txt
repo_stream-1.3.1.dist-info/RECORD
