Metadata-Version: 2.1
Name: repo-stream
Version: 1.3.1
Summary: Cron-based remote pre-commit executions by opening pull requests.
Home-page: https://github.com/mondeja/repo-stream
Author: Álvaro Mondéjar Rubio
Author-email: mondejar1994@gmail.com
License: BSD-3-Clause
Platform: UNKNOWN
Classifier: License :: OSI Approved :: BSD License
Classifier: Programming Language :: Python
Classifier: Programming Language :: Python :: 3
Classifier: Programming Language :: Python :: 3 :: Only
Classifier: Programming Language :: Python :: 3.6
Classifier: Programming Language :: Python :: 3.7
Classifier: Programming Language :: Python :: 3.8
Classifier: Programming Language :: Python :: 3.9
Classifier: Programming Language :: Python :: 3.10
Requires-Python: >=3.6
Requires-Dist: pre-commit
Requires-Dist: pyyaml
Provides-Extra: dev
Requires-Dist: bump2version ; extra == 'dev'
Requires-Dist: flake8 (==3.9.2) ; extra == 'dev'
Requires-Dist: flake8-implicit-str-concat (==0.2.0) ; extra == 'dev'
Requires-Dist: flake8-print (==4.0.0) ; extra == 'dev'
Requires-Dist: isort (==5.9.1) ; extra == 'dev'
Requires-Dist: pytest (==6.2.5) ; extra == 'dev'
Requires-Dist: pytest-cov (==3.0.0) ; extra == 'dev'
Requires-Dist: yamllint (==1.26.1) ; extra == 'dev'
Provides-Extra: lint
Requires-Dist: flake8 (==3.9.2) ; extra == 'lint'
Requires-Dist: flake8-implicit-str-concat (==0.2.0) ; extra == 'lint'
Requires-Dist: flake8-print (==4.0.0) ; extra == 'lint'
Requires-Dist: isort (==5.9.1) ; extra == 'lint'
Requires-Dist: yamllint (==1.26.1) ; extra == 'lint'
Provides-Extra: test
Requires-Dist: pytest (==6.2.5) ; extra == 'test'
Requires-Dist: pytest-cov (==3.0.0) ; extra == 'test'
